ch/__init__.py
ch/epfl/__init__.py
ch/epfl/biop/__init__.py
ch/epfl/biop/scijava/__init__.py
ch/epfl/biop/scijava/command/__init__.py
ch/epfl/biop/scijava/command/spimdata.py
de/__init__.py
de/mpicbg/__init__.py
de/mpicbg/scf/__init__.py
de/mpicbg/scf/imgtools/__init__.py
de/mpicbg/scf/imgtools/image/__init__.py
de/mpicbg/scf/imgtools/image/create/__init__.py
de/mpicbg/scf/imgtools/image/create/image.py
de/mpicbg/scf/imgtools/image/create/labelmap.py
fiji/__init__.py
fiji/plugin/__init__.py
fiji/plugin/trackmate/__init__.py
fiji/plugin/trackmate/action/LabelImgExporter.py
fiji/plugin/trackmate/action/__init__.py
fiji/plugin/trackmate/cellpose/CellposeSettings.py
fiji/plugin/trackmate/cellpose/__init__.py
fiji/plugin/trackmate/detection.py
fiji/plugin/trackmate/features.py
fiji/plugin/trackmate/stardist.py
fiji/plugin/trackmate/tracking/__init__.py
fiji/plugin/trackmate/tracking/jaqaman.py
fr/__init__.py
fr/igred/__init__.py
fr/igred/omero/__init__.py
fr/igred/omero/annotations.py
fr/igred/omero/roi.py
ij/__init__.py
ij/io.py
ij/measure.py
ij/plugin/__init__.py
ij/plugin/filter.py
ij/plugin/frame.py
ij/process.py
inra/__init__.py
inra/ijpb/__init__.py
inra/ijpb/label.py
inra/ijpb/plugins.py
java/__init__.py
java/io/__init__.py
java/lang/System.py
java/lang/__init__.py
java/text/__init__.py
java/util/__init__.py
javax/__init__.py
javax/xml/__init__.py
javax/xml/parsers/__init__.py
loci/__init__.py
loci/common/__init__.py
loci/formats/__init__.py
loci/formats/_in.py
loci/plugins/__init__.py
loci/plugins/_in.py
mcib3d/__init__.py
mcib3d/geom.py
mcib3d/image3d/__init__.py
mcib3d/image3d/processing.py
net/__init__.py
net/imagej/__init__.py
net/imagej/axis/__init__.py
net/imagej/ops/__init__.py
net/imglib2/__init__.py
net/imglib2/img.py
omero/__init__.py
omero/cmd/__init__.py
omero/gateway/__init__.py
omero/gateway/model.py
org/__init__.py
org/scijava/__init__.py
org/scijava/widget/__init__.py
org/xml/__init__.py
org/xml/sax/__init__.py
imcf_fiji_mocks-0.13.0.dist-info/METADATA
imcf_fiji_mocks-0.13.0.dist-info/WHEEL
imcf_fiji_mocks-0.13.0.dist-info/RECORD
