Metadata-Version: 2.3
Name: imcf-fiji-mocks
Version: 0.13.0
Summary: Mocks collection for Fiji-Python. Zero functional code.
Author: Niko Ehrenfeuchter
Author-email: nikolaus.ehrenfeuchter@unibas.ch
Requires-Python: >=2.7
Classifier: Programming Language :: Python :: 2
Classifier: Programming Language :: Python :: 2.7
Classifier: Programming Language :: Python :: 3
Classifier: Programming Language :: Python :: 3.4
Classifier: Programming Language :: Python :: 3.5
Classifier: Programming Language :: Python :: 3.6
Classifier: Programming Language :: Python :: 3.7
Classifier: Programming Language :: Python :: 3.8
Classifier: Programming Language :: Python :: 3.9
Classifier: Programming Language :: Python :: 3.10
Classifier: Programming Language :: Python :: 3.11
Classifier: Programming Language :: Python :: 3.12
Classifier: Programming Language :: Python :: 3.13
